{
  "method": "LightGCN window-retrain",
  "warmup_time_s": 1.3,
  "stream_time_s": 5.3,
  "total_time_s": 6.6,
  "avg_recall10": 0.08816074774180863,
  "avg_ndcg10": 0.1798423294535254,
  "avg_recall20": 0.14523582956174041,
  "avg_ndcg20": 0.17506446153600055,
  "batches": [
    {
      "batch": 1,
      "metrics": {
        "Recall@10": 0.09599061138891307,
        "Recall@20": 0.14560238342328186,
        "NDCG@10": 0.1822744440446699,
        "NDCG@20": 0.17443127434908434
      }
    },
    {
      "batch": 2,
      "metrics": {
        "Recall@10": 0.0871236674545225,
        "Recall@20": 0.1384061194622325,
        "NDCG@10": 0.18118558932177303,
        "NDCG@20": 0.17291722499729492
      }
    },
    {
      "batch": 3,
      "metrics": {
        "Recall@10": 0.07238953002185976,
        "Recall@20": 0.1331455390390394,
        "NDCG@10": 0.17375019270039854,
        "NDCG@20": 0.16862720796782055
      }
    },
    {
      "batch": 4,
      "metrics": {
        "Recall@10": 0.08191069313784868,
        "Recall@20": 0.1324523025629803,
        "NDCG@10": 0.15321782949487678,
        "NDCG@20": 0.1527857602486087
      }
    },
    {
      "batch": 5,
      "metrics": {
        "Recall@10": 0.08198355953453004,
        "Recall@20": 0.13521451256215442,
        "NDCG@10": 0.16107631973439562,
        "NDCG@20": 0.1584104038295502
      }
    },
    {
      "batch": 6,
      "metrics": {
        "Recall@10": 0.08661158049542077,
        "Recall@20": 0.14290178768775702,
        "NDCG@10": 0.16829314906442186,
        "NDCG@20": 0.16434744091240006
      }
    },
    {
      "batch": 7,
      "metrics": {
        "Recall@10": 0.09311814409020254,
        "Recall@20": 0.15604829500090173,
        "NDCG@10": 0.189182054584122,
        "NDCG@20": 0.18611850723963605
      }
    },
    {
      "batch": 8,
      "metrics": {
        "Recall@10": 0.0908513388737731,
        "Recall@20": 0.1529442333607091,
        "NDCG@10": 0.2123413870401338,
        "NDCG@20": 0.20200324248352103
      }
    },
    {
      "batch": 9,
      "metrics": {
        "Recall@10": 0.09109940542229843,
        "Recall@20": 0.14988110395970666,
        "NDCG@10": 0.17429357540273754,
        "NDCG@20": 0.1719443846328203
      }
    },
    {
      "batch": 10,
      "metrics": {
        "Recall@10": 0.10052894699871748,
        "Recall@20": 0.16576201855864126,
        "NDCG@10": 0.2028087531477251,
        "NDCG@20": 0.19905916869926923
      }
    }
  ],
  "seed": 43,
  "hyperparams": {
    "window_size": 50000
  },
  "dataset": "ml-10m",
  "kcore": null
}