{
  "method": "LightGCN window-retrain",
  "warmup_time_s": 1.7,
  "stream_time_s": 6.1,
  "total_time_s": 7.8,
  "avg_recall10": 0.09351860339284436,
  "avg_ndcg10": 0.1894852752281469,
  "avg_recall20": 0.15510888207750073,
  "avg_ndcg20": 0.18559580178519483,
  "batches": [
    {
      "batch": 1,
      "metrics": {
        "Recall@10": 0.1057272081631259,
        "Recall@20": 0.17143378650024085,
        "NDCG@10": 0.20244761105378847,
        "NDCG@20": 0.19699754702239025
      }
    },
    {
      "batch": 2,
      "metrics": {
        "Recall@10": 0.08778195254847247,
        "Recall@20": 0.14284609163619996,
        "NDCG@10": 0.18495140296710902,
        "NDCG@20": 0.17932174229924028
      }
    },
    {
      "batch": 3,
      "metrics": {
        "Recall@10": 0.08511218197401041,
        "Recall@20": 0.1468333247538907,
        "NDCG@10": 0.17744194002720615,
        "NDCG@20": 0.17604556972379032
      }
    },
    {
      "batch": 4,
      "metrics": {
        "Recall@10": 0.09092799912057542,
        "Recall@20": 0.1450823053489381,
        "NDCG@10": 0.17190095201889066,
        "NDCG@20": 0.1699795553925612
      }
    },
    {
      "batch": 5,
      "metrics": {
        "Recall@10": 0.0836753340678472,
        "Recall@20": 0.1473945568067175,
        "NDCG@10": 0.17191617312330917,
        "NDCG@20": 0.1692709319941309
      }
    },
    {
      "batch": 6,
      "metrics": {
        "Recall@10": 0.09135667254243254,
        "Recall@20": 0.14742880655072593,
        "NDCG@10": 0.17631070048085226,
        "NDCG@20": 0.17242160642100823
      }
    },
    {
      "batch": 7,
      "metrics": {
        "Recall@10": 0.09547401363004832,
        "Recall@20": 0.16122895221001493,
        "NDCG@10": 0.19032773851796775,
        "NDCG@20": 0.18868313340199325
      }
    },
    {
      "batch": 8,
      "metrics": {
        "Recall@10": 0.08956368290088028,
        "Recall@20": 0.15178317850441178,
        "NDCG@10": 0.20451386201880323,
        "NDCG@20": 0.19910183220132777
      }
    },
    {
      "batch": 9,
      "metrics": {
        "Recall@10": 0.10019033391214603,
        "Recall@20": 0.16730405243260874,
        "NDCG@10": 0.20650821365869576,
        "NDCG@20": 0.2021193391017865
      }
    },
    {
      "batch": 10,
      "metrics": {
        "Recall@10": 0.10537665506890499,
        "Recall@20": 0.1697537660312589,
        "NDCG@10": 0.20853415841484657,
        "NDCG@20": 0.20201676029371957
      }
    }
  ],
  "seed": 46,
  "hyperparams": {
    "window_size": 50000
  },
  "dataset": "ml-10m",
  "kcore": null
}