{
  "method": "LightGCN window-retrain",
  "warmup_time_s": 1.7,
  "stream_time_s": 6.5,
  "total_time_s": 8.2,
  "avg_recall10": 0.09075484029914019,
  "avg_ndcg10": 0.1854085844661533,
  "avg_recall20": 0.14874676589037267,
  "avg_ndcg20": 0.18103733826269908,
  "batches": [
    {
      "batch": 1,
      "metrics": {
        "Recall@10": 0.09021228759234023,
        "Recall@20": 0.148159477365889,
        "NDCG@10": 0.1940263385251178,
        "NDCG@20": 0.1874052388332585
      }
    },
    {
      "batch": 2,
      "metrics": {
        "Recall@10": 0.08168737373926659,
        "Recall@20": 0.1392993142737817,
        "NDCG@10": 0.1820667914936588,
        "NDCG@20": 0.1789317913764256
      }
    },
    {
      "batch": 3,
      "metrics": {
        "Recall@10": 0.08763383404783807,
        "Recall@20": 0.1394521902289317,
        "NDCG@10": 0.17302044332688205,
        "NDCG@20": 0.1682426506800823
      }
    },
    {
      "batch": 4,
      "metrics": {
        "Recall@10": 0.09777353238609016,
        "Recall@20": 0.15431161137993857,
        "NDCG@10": 0.1995913473336955,
        "NDCG@20": 0.19180959642236522
      }
    },
    {
      "batch": 5,
      "metrics": {
        "Recall@10": 0.0867766345858789,
        "Recall@20": 0.1475128946121615,
        "NDCG@10": 0.17975741778281207,
        "NDCG@20": 0.17762778922945177
      }
    },
    {
      "batch": 6,
      "metrics": {
        "Recall@10": 0.08975806562291731,
        "Recall@20": 0.14749661724877414,
        "NDCG@10": 0.18945212540192152,
        "NDCG@20": 0.18677175578031122
      }
    },
    {
      "batch": 7,
      "metrics": {
        "Recall@10": 0.09686967638135814,
        "Recall@20": 0.15295922781252028,
        "NDCG@10": 0.17831423839052332,
        "NDCG@20": 0.17435939834649214
      }
    },
    {
      "batch": 8,
      "metrics": {
        "Recall@10": 0.08510589143235042,
        "Recall@20": 0.13974109142410257,
        "NDCG@10": 0.1830177882759397,
        "NDCG@20": 0.17619475854893626
      }
    },
    {
      "batch": 9,
      "metrics": {
        "Recall@10": 0.09534301168904273,
        "Recall@20": 0.15347951269037088,
        "NDCG@10": 0.18536910581984792,
        "NDCG@20": 0.1826194638301721
      }
    },
    {
      "batch": 10,
      "metrics": {
        "Recall@10": 0.09638809551431941,
        "Recall@20": 0.1650557218672561,
        "NDCG@10": 0.18947024831113438,
        "NDCG@20": 0.1864109395794955
      }
    }
  ],
  "seed": 43,
  "hyperparams": {
    "window_size": 50000
  },
  "dataset": "ml-20m",
  "kcore": null
}