{
  "method": "SimGCL warm-start",
  "warmup_time_s": 5.0,
  "stream_time_s": 141.2,
  "total_time_s": 146.2,
  "avg_recall10": 0.08377914891376946,
  "avg_ndcg10": 0.17788776810332746,
  "avg_recall20": 0.1409119908019592,
  "avg_ndcg20": 0.1730638905338672,
  "batches": [
    {
      "batch": 1,
      "metrics": {
        "Recall@10": 0.08550023178654685,
        "Recall@20": 0.14445402708292232,
        "NDCG@10": 0.17427377404780678,
        "NDCG@20": 0.17166375464309172
      }
    },
    {
      "batch": 2,
      "metrics": {
        "Recall@10": 0.0785938873348718,
        "Recall@20": 0.14182400292678382,
        "NDCG@10": 0.17864946723056008,
        "NDCG@20": 0.17644073138955352
      }
    },
    {
      "batch": 3,
      "metrics": {
        "Recall@10": 0.0892259511409077,
        "Recall@20": 0.14997627977954783,
        "NDCG@10": 0.175009034711452,
        "NDCG@20": 0.173067350709584
      }
    },
    {
      "batch": 4,
      "metrics": {
        "Recall@10": 0.09426089471733178,
        "Recall@20": 0.14766246123445423,
        "NDCG@10": 0.17461909834639558,
        "NDCG@20": 0.17147223364348474
      }
    },
    {
      "batch": 5,
      "metrics": {
        "Recall@10": 0.08099182208241225,
        "Recall@20": 0.1272339919800091,
        "NDCG@10": 0.1876275526165355,
        "NDCG@20": 0.1765450876990641
      }
    },
    {
      "batch": 6,
      "metrics": {
        "Recall@10": 0.08149824419455953,
        "Recall@20": 0.12990871352206493,
        "NDCG@10": 0.19337464554255543,
        "NDCG@20": 0.1827328624762007
      }
    },
    {
      "batch": 7,
      "metrics": {
        "Recall@10": 0.08251173949233331,
        "Recall@20": 0.14969466322715652,
        "NDCG@10": 0.1693631635963294,
        "NDCG@20": 0.16709827836248237
      }
    },
    {
      "batch": 8,
      "metrics": {
        "Recall@10": 0.07715649536394412,
        "Recall@20": 0.13510360977441843,
        "NDCG@10": 0.17494162719921186,
        "NDCG@20": 0.17044009767255608
      }
    },
    {
      "batch": 9,
      "metrics": {
        "Recall@10": 0.07351499309736402,
        "Recall@20": 0.1285813943418554,
        "NDCG@10": 0.16329863974106382,
        "NDCG@20": 0.1597968820526929
      }
    },
    {
      "batch": 10,
      "metrics": {
        "Recall@10": 0.09453722992742329,
        "Recall@20": 0.15468076415037949,
        "NDCG@10": 0.1877206780013642,
        "NDCG@20": 0.18138162668996183
      }
    }
  ],
  "seed": 46,
  "hyperparams": {
    "eps": 0.2,
    "lambda_cl": 0.2,
    "temperature": 0.2
  },
  "dataset": "ml-20m",
  "kcore": null
}